Workbook

Sheet README
A1: How to use this workbook
A3: Purpose | B3: The full universe of Indian economic indicators the tracker can collect, with how to get each one and how much history exists. Each CATALOGUE row is an indicator FAMILY – one row can expand into dozens or thousands of individual series (states × sectors × items × base years).
A4: What to do | B4: In CATALOGUE, fill the yellow 'Your decision' column: Include (build it), Later (next phase), Skip. Add comments in 'Team notes'. The SUMMARY sheet updates automatically.
A5: Example | B5: CPI (base 2024) – All-India general index → Your decision: Include · Team notes: 'Core dashboard; need rural/urban split'.
A6: Priority | B6: P1 = core macro dashboard · P2 = extended analysis · P3 = deep / reference / infrequent surveys.
A7: Build tier | B7: T1 = MoSPI official API (easiest) · T1b = other APIs (data.gov.in, Yahoo, World Bank, IMF…) · T2 = structured Excel/CSV downloads · T3 = scrapers & PDF parsing · T4 = paid/licensed or manual once-a-year.
A8: Verification | B8: Verified by your test = you ran it and saw the data · Partly verified = one of its sources verified (e.g. Yahoo fallback), the official one not yet · Listed by API = the API lists it, history not checked yet (mostly one-off surveys) · Code verified, name to map = NAS code works but its name couldn't be listed · Not yet tested = known source, not yet tried · Depends on inputs = computed by us.
A9: History | B9: For verified MoSPI rows this is exactly what your test found. For other rows it is an expectation to be checked.
A10: Sheets | B10: SUMMARY (live counts) · CATALOGUE (the master list) · MOSPI_VERIFIED (your test results) · NAS_CODES (GDP code availability) · RBI_API_39 (RBI data via MoSPI) · YAHOO_TICKERS (market tickers) · FUTURE_PROOFING (design principles).
A11: Licensing | B11: Internal team use only. PMI and private real-estate data are licensed – use public headlines only. Yahoo Finance is unofficial; keep it internal and don't redistribute.

Sheet SUMMARY
A1: India Economic Database – Indicator Universe
A2: FinSkeptics internal use only · updated 11-Sep-2026 with all test results · counts are live formulas over CATALOGUE
A4: By theme
A5: Category | B5: Indicator families | C5: Included | D5: Later | E5: Skipped
A6: 01 National Accounts | B6: =COUNTIF(CATALOGUE!$B$2:$B$207,A6) -> 14 | C6: =COUNTIFS(CATALOGUE!$B$2:$B$207,A6,CATALOGUE!$O$2:$O$207,"Include") -> 0 | D6: =COUNTIFS(CATALOGUE!$B$2:$B$207,A6,CATALOGUE!$O$2:$O$207,"Later") -> 0 | E6: =COUNTIFS(CATALOGUE!$B$2:$B$207,A6,CATALOGUE!$O$2:$O$207,"Skip") -> 0
A7: 02 Prices & Inflation | B7: =COUNTIF(CATALOGUE!$B$2:$B$207,A7) -> 22 | C7: =COUNTIFS(CATALOGUE!$B$2:$B$207,A7,CATALOGUE!$O$2:$O$207,"Include") -> 0 | D7: =COUNTIFS(CATALOGUE!$B$2:$B$207,A7,CATALOGUE!$O$2:$O$207,"Later") -> 0 | E7: =COUNTIFS(CATALOGUE!$B$2:$B$207,A7,CATALOGUE!$O$2:$O$207,"Skip") -> 0
A8: 03 Industry & Production | B8: =COUNTIF(CATALOGUE!$B$2:$B$207,A8) -> 17 | C8: =COUNTIFS(CATALOGUE!$B$2:$B$207,A8,CATALOGUE!$O$2:$O$207,"Include") -> 0 | D8: =COUNTIFS(CATALOGUE!$B$2:$B$207,A8,CATALOGUE!$O$2:$O$207,"Later") -> 0 | E8: =COUNTIFS(CATALOGUE!$B$2:$B$207,A8,CATALOGUE!$O$2:$O$207,"Skip") -> 0
A9: 04 Services & High-Frequency Activity | B9: =COUNTIF(CATALOGUE!$B$2:$B$207,A9) -> 11 | C9: =COUNTIFS(CATALOGUE!$B$2:$B$207,A9,CATALOGUE!$O$2:$O$207,"Include") -> 0 | D9: =COUNTIFS(CATALOGUE!$B$2:$B$207,A9,CATALOGUE!$O$2:$O$207,"Later") -> 0 | E9: =COUNTIFS(CATALOGUE!$B$2:$B$207,A9,CATALOGUE!$O$2:$O$207,"Skip") -> 0
A10: 05 Labour & Employment | B10: =COUNTIF(CATALOGUE!$B$2:$B$207,A10) -> 10 | C10: =COUNTIFS(CATALOGUE!$B$2:$B$207,A10,CATALOGUE!$O$2:$O$207,"Include") -> 0 | D10: =COUNTIFS(CATALOGUE!$B$2:$B$207,A10,CATALOGUE!$O$2:$O$207,"Later") -> 0 | E10: =COUNTIFS(CATALOGUE!$B$2:$B$207,A10,CATALOGUE!$O$2:$O$207,"Skip") -> 0
A11: 06 Money, Banking & Credit | B11: =COUNTIF(CATALOGUE!$B$2:$B$207,A11) -> 16 | C11: =COUNTIFS(CATALOGUE!$B$2:$B$207,A11,CATALOGUE!$O$2:$O$207,"Include") -> 0 | D11: =COUNTIFS(CATALOGUE!$B$2:$B$207,A11,CATALOGUE!$O$2:$O$207,"Later") -> 0 | E11: =COUNTIFS(CATALOGUE!$B$2:$B$207,A11,CATALOGUE!$O$2:$O$207,"Skip") -> 0
A12: 07 Financial Markets | B12: =COUNTIF(CATALOGUE!$B$2:$B$207,A12) -> 20 | C12: =COUNTIFS(CATALOGUE!$B$2:$B$207,A12,CATALOGUE!$O$2:$O$207,"Include") -> 0 | D12: =COUNTIFS(CATALOGUE!$B$2:$B$207,A12,CATALOGUE!$O$2:$O$207,"Later") -> 0 | E12: =COUNTIFS(CATALOGUE!$B$2:$B$207,A12,CATALOGUE!$O$2:$O$207,"Skip") -> 0
A13: 08 External Sector | B13: =COUNTIF(CATALOGUE!$B$2:$B$207,A13) -> 19 | C13: =COUNTIFS(CATALOGUE!$B$2:$B$207,A13,CATALOGUE!$O$2:$O$207,"Include") -> 0 | D13: =COUNTIFS(CATALOGUE!$B$2:$B$207,A13,CATALOGUE!$O$2:$O$207,"Later") -> 0 | E13: =COUNTIFS(CATALOGUE!$B$2:$B$207,A13,CATALOGUE!$O$2:$O$207,"Skip") -> 0
A14: 09 Fiscal | B14: =COUNTIF(CATALOGUE!$B$2:$B$207,A14) -> 9 | C14: =COUNTIFS(CATALOGUE!$B$2:$B$207,A14,CATALOGUE!$O$2:$O$207,"Include") -> 0 | D14: =COUNTIFS(CATALOGUE!$B$2:$B$207,A14,CATALOGUE!$O$2:$O$207,"Later") -> 0 | E14: =COUNTIFS(CATALOGUE!$B$2:$B$207,A14,CATALOGUE!$O$2:$O$207,"Skip") -> 0
A15: 10 Agriculture & Rural | B15: =COUNTIF(CATALOGUE!$B$2:$B$207,A15) -> 8 | C15: =COUNTIFS(CATALOGUE!$B$2:$B$207,A15,CATALOGUE!$O$2:$O$207,"Include") -> 0 | D15: =COUNTIFS(CATALOGUE!$B$2:$B$207,A15,CATALOGUE!$O$2:$O$207,"Later") -> 0 | E15: =COUNTIFS(CATALOGUE!$B$2:$B$207,A15,CATALOGUE!$O$2:$O$207,"Skip") -> 0
A16: 11 Energy | B16: =COUNTIF(CATALOGUE!$B$2:$B$207,A16) -> 9 | C16: =COUNTIFS(CATALOGUE!$B$2:$B$207,A16,CATALOGUE!$O$2:$O$207,"Include") -> 0 | D16: =COUNTIFS(CATALOGUE!$B$2:$B$207,A16,CATALOGUE!$O$2:$O$207,"Later") -> 0 | E16: =COUNTIFS(CATALOGUE!$B$2:$B$207,A16,CATALOGUE!$O$2:$O$207,"Skip") -> 0
A17: 12 Real Estate & Construction | B17: =COUNTIF(CATALOGUE!$B$2:$B$207,A17) -> 4 | C17: =COUNTIFS(CATALOGUE!$B$2:$B$207,A17,CATALOGUE!$O$2:$O$207,"Include") -> 0 | D17: =COUNTIFS(CATALOGUE!$B$2:$B$207,A17,CATALOGUE!$O$2:$O$207,"Later") -> 0 | E17: =COUNTIFS(CATALOGUE!$B$2:$B$207,A17,CATALOGUE!$O$2:$O$207,"Skip") -> 0
... A22: 17 Derived Analytics (computed by us) | B22: =COUNTIF(CATALOGUE!$B$2:$B$207,A22) -> 14 | C22: =COUNTIFS(CATALOGUE!$B$2:$B$207,A22,CATALOGUE!$O$2:$O$207,"Include") -> 0 | D22: =COUNTIFS(CATALOGUE!$B$2:$B$207,A22,CATALOGUE!$O$2:$O$207,"Later") -> 0 | E22: =COUNTIFS(CATALOGUE!$B$2:$B$207,A22,CATALOGUE!$O$2:$O$207,"Skip") -> 0
A23: Total | B23: =SUM(B6:B22) -> 206 | C23: =SUM(C6:C22) -> 0 | D23: =SUM(D6:D22) -> 0 | E23: =SUM(E6:E22) -> 0
A25: By priority
A26: Category | B26: Indicator families | C26: Included | D26: Later | E26: Skipped
A27: P1 | B27: =COUNTIF(CATALOGUE!$L$2:$L$207,A27) -> 74 | C27: =COUNTIFS(CATALOGUE!$L$2:$L$207,A27,CATALOGUE!$O$2:$O$207,"Include") -> 0 | D27: =COUNTIFS(CATALOGUE!$L$2:$L$207,A27,CATALOGUE!$O$2:$O$207,"Later") -> 0 | E27: =COUNTIFS(CATALOGUE!$L$2:$L$207,A27,CATALOGUE!$O$2:$O$207,"Skip") -> 0
A28: P2 | B28: =COUNTIF(CATALOGUE!$L$2:$L$207,A28) -> 81 | C28: =COUNTIFS(CATALOGUE!$L$2:$L$207,A28,CATALOGUE!$O$2:$O$207,"Include") -> 0 | D28: =COUNTIFS(CATALOGUE!$L$2:$L$207,A28,CATALOGUE!$O$2:$O$207,"Later") -> 0 | E28: =COUNTIFS(CATALOGUE!$L$2:$L$207,A28,CATALOGUE!$O$2:$O$207,"Skip") -> 0
A29: P3 | B29: =COUNTIF(CATALOGUE!$L$2:$L$207,A29) -> 51 | C29: =COUNTIFS(CATALOGUE!$L$2:$L$207,A29,CATALOGUE!$O$2:$O$207,"Include") -> 0 | D29: =COUNTIFS(CATALOGUE!$L$2:$L$207,A29,CATALOGUE!$O$2:$O$207,"Later") -> 0 | E29: =COUNTIFS(CATALOGUE!$L$2:$L$207,A29,CATALOGUE!$O$2:$O$207,"Skip") -> 0
A30: Total | B30: =SUM(B27:B29) -> 206 | C30: =SUM(C27:C29) -> 0 | D30: =SUM(D27:D29) -> 0 | E30: =SUM(E27:E29) -> 0
A32: By access method
A33: Category | B33: Indicator families | C33: Included | D33: Later | E33: Skipped
A34: API – free key | B34: =COUNTIF(CATALOGUE!$H$2:$H$207,A34) -> 3 | C34: =COUNTIFS(CATALOGUE!$H$2:$H$207,A34,CATALOGUE!$O$2:$O$207,"Include") -> 0 | D34: =COUNTIFS(CATALOGUE!$H$2:$H$207,A34,CATALOGUE!$O$2:$O$207,"Later") -> 0 | E34: =COUNTIFS(CATALOGUE!$H$2:$H$207,A34,CATALOGUE!$O$2:$O$207,"Skip") -> 0
A35: API – no key | B35: =COUNTIF(CATALOGUE!$H$2:$H$207,A35) -> 6 | C35: =COUNTIFS(CATALOGUE!$H$2:$H$207,A35,CATALOGUE!$O$2:$O$207,"Include") -> 0 | D35: =COUNTIFS(CATALOGUE!$H$2:$H$207,A35,CATALOGUE!$O$2:$O$207,"Later") -> 0 | E35: =COUNTIFS(CATALOGUE!$H$2:$H$207,A35,CATALOGUE!$O$2:$O$207,"Skip") -> 0
A36: API – official package | B36: =COUNTIF(CATALOGUE!$H$2:$H$207,A36) -> 67 | C36: =COUNTIFS(CATALOGUE!$H$2:$H$207,A36,CATALOGUE!$O$2:$O$207,"Include") -> 0 | D36: =COUNTIFS(CATALOGUE!$H$2:$H$207,A36,CATALOGUE!$O$2:$O$207,"Later") -> 0 | E36: =COUNTIFS(CATALOGUE!$H$2:$H$207,A36,CATALOGUE!$O$2:$O$207,"Skip") -> 0
A37: API – unofficial | B37: =COUNTIF(CATALOGUE!$H$2:$H$207,A37) -> 7 | C37: =COUNTIFS(CATALOGUE!$H$2:$H$207,A37,CATALOGUE!$O$2:$O$207,"Include") -> 0 | D37: =COUNTIFS(CATALOGUE!$H$2:$H$207,A37,CATALOGUE!$O$2:$O$207,"Later") -> 0 | E37: =COUNTIFS(CATALOGUE!$H$2:$H$207,A37,CATALOGUE!$O$2:$O$207,"Skip") -> 0
A38: Derived (computed) | B38: =COUNTIF(CATALOGUE!$H$2:$H$207,A38) -> 19 | C38: =COUNTIFS(CATALOGUE!$H$2:$H$207,A38,CATALOGUE!$O$2:$O$207,"Include") -> 0 | D38: =COUNTIFS(CATALOGUE!$H$2:$H$207,A38,CATALOGUE!$O$2:$O$207,"Later") -> 0 | E38: =COUNTIFS(CATALOGUE!$H$2:$H$207,A38,CATALOGUE!$O$2:$O$207,"Skip") -> 0
A39: Download (Excel/CSV) | B39: =COUNTIF(CATALOGUE!$H$2:$H$207,A39) -> 54 | C39: =COUNTIFS(CATALOGUE!$H$2:$H$207,A39,CATALOGUE!$O$2:$O$207,"Include") -> 0 | D39: =COUNTIFS(CATALOGUE!$H$2:$H$207,A39,CATALOGUE!$O$2:$O$207,"Later") -> 0 | E39: =COUNTIFS(CATALOGUE!$H$2:$H$207,A39,CATALOGUE!$O$2:$O$207,"Skip") -> 0
A40: Manual (annual) | B40: =COUNTIF(CATALOGUE!$H$2:$H$207,A40) -> 2 | C40: =COUNTIFS(CATALOGUE!$H$2:$H$207,A40,CATALOGUE!$O$2:$O$207,"Include") -> 0 | D40: =COUNTIFS(CATALOGUE!$H$2:$H$207,A40,CATALOGUE!$O$2:$O$207,"Later") -> 0 | E40: =COUNTIFS(CATALOGUE!$H$2:$H$207,A40,CATALOGUE!$O$2:$O$207,"Skip") -> 0
A41: PDF parse | B41: =COUNTIF(CATALOGUE!$H$2:$H$207,A41) -> 22 | C41: =COUNTIFS(CATALOGUE!$H$2:$H$207,A41,CATALOGUE!$O$2:$O$207,"Include") -> 0 | D41: =COUNTIFS(CATALOGUE!$H$2:$H$207,A41,CATALOGUE!$O$2:$O$207,"Later") -> 0 | E41: =COUNTIFS(CATALOGUE!$H$2:$H$207,A41,CATALOGUE!$O$2:$O$207,"Skip") -> 0
A42: Paid / licensed | B42: =COUNTIF(CATALOGUE!$H$2:$H$207,A42) -> 2 | C42: =COUNTIFS(CATALOGUE!$H$2:$H$207,A42,CATALOGUE!$O$2:$O$207,"Include") -> 0 | D42: =COUNTIFS(CATALOGUE!$H$2:$H$207,A42,CATALOGUE!$O$2:$O$207,"Later") -> 0 | E42: =COUNTIFS(CATALOGUE!$H$2:$H$207,A42,CATALOGUE!$O$2:$O$207,"Skip") -> 0
A43: Scrape (HTML) | B43: =COUNTIF(CATALOGUE!$H$2:$H$207,A43) -> 24 | C43: =COUNTIFS(CATALOGUE!$H$2:$H$207,A43,CATALOGUE!$O$2:$O$207,"Include") -> 0 | D43: =COUNTIFS(CATALOGUE!$H$2:$H$207,A43,CATALOGUE!$O$2:$O$207,"Later") -> 0 | E43: =COUNTIFS(CATALOGUE!$H$2:$H$207,A43,CATALOGUE!$O$2:$O$207,"Skip") -> 0
A44: Total | B44: =SUM(B34:B43) -> 206 | C44: =SUM(C34:C43) -> 0 | D44: =SUM(D34:D43) -> 0 | E44: =SUM(E34:E43) -> 0
A46: By build tier
A47: Category | B47: Indicator families | C47: Included | D47: Later | E47: Skipped
A48: T1 | B48: =COUNTIF(CATALOGUE!$M$2:$M$207,A48) -> 77 | C48: =COUNTIFS(CATALOGUE!$M$2:$M$207,A48,CATALOGUE!$O$2:$O$207,"Include") -> 0 | D48: =COUNTIFS(CATALOGUE!$M$2:$M$207,A48,CATALOGUE!$O$2:$O$207,"Later") -> 0 | E48: =COUNTIFS(CATALOGUE!$M$2:$M$207,A48,CATALOGUE!$O$2:$O$207,"Skip") -> 0
A49: T1b | B49: =COUNTIF(CATALOGUE!$M$2:$M$207,A49) -> 16 | C49: =COUNTIFS(CATALOGUE!$M$2:$M$207,A49,CATALOGUE!$O$2:$O$207,"Include") -> 0 | D49: =COUNTIFS(CATALOGUE!$M$2:$M$207,A49,CATALOGUE!$O$2:$O$207,"Later") -> 0 | E49: =COUNTIFS(CATALOGUE!$M$2:$M$207,A49,CATALOGUE!$O$2:$O$207,"Skip") -> 0
A50: T2 | B50: =COUNTIF(CATALOGUE!$M$2:$M$207,A50) -> 60 | C50: =COUNTIFS(CATALOGUE!$M$2:$M$207,A50,CATALOGUE!$O$2:$O$207,"Include") -> 0 | D50: =COUNTIFS(CATALOGUE!$M$2:$M$207,A50,CATALOGUE!$O$2:$O$207,"Later") -> 0 | E50: =COUNTIFS(CATALOGUE!$M$2:$M$207,A50,CATALOGUE!$O$2:$O$207,"Skip") -> 0
A51: T3 | B51: =COUNTIF(CATALOGUE!$M$2:$M$207,A51) -> 47 | C51: =COUNTIFS(CATALOGUE!$M$2:$M$207,A51,CATALOGUE!$O$2:$O$207,"Include") -> 0 | D51: =COUNTIFS(CATALOGUE!$M$2:$M$207,A51,CATALOGUE!$O$2:$O$207,"Later") -> 0 | E51: =COUNTIFS(CATALOGUE!$M$2:$M$207,A51,CATALOGUE!$O$2:$O$207,"Skip") -> 0
A52: T4 | B52: =COUNTIF(CATALOGUE!$M$2:$M$207,A52) -> 6 | C52: =COUNTIFS(CATALOGUE!$M$2:$M$207,A52,CATALOGUE!$O$2:$O$207,"Include") -> 0 | D52: =COUNTIFS(CATALOGUE!$M$2:$M$207,A52,CATALOGUE!$O$2:$O$207,"Later") -> 0 | E52: =COUNTIFS(CATALOGUE!$M$2:$M$207,A52,CATALOGUE!$O$2:$O$207,"Skip") -> 0
A53: Total | B53: =SUM(B48:B52) -> 206 | C53: =SUM(C48:C52) -> 0 | D53: =SUM(D48:D52) -> 0 | E53: =SUM(E48:E52) -> 0
A55: By verification status
A56: Category | B56: Indicator families | C56: Included | D56: Later | E56: Skipped
A57: Code verified, name to map | B57: =COUNTIF(CATALOGUE!$K$2:$K$207,A57) -> 10 | C57: =COUNTIFS(CATALOGUE!$K$2:$K$207,A57,CATALOGUE!$O$2:$O$207,"Include") -> 0 | D57: =COUNTIFS(CATALOGUE!$K$2:$K$207,A57,CATALOGUE!$O$2:$O$207,"Later") -> 0 | E57: =COUNTIFS(CATALOGUE!$K$2:$K$207,A57,CATALOGUE!$O$2:$O$207,"Skip") -> 0
A58: Depends on inputs | B58: =COUNTIF(CATALOGUE!$K$2:$K$207,A58) -> 19 | C58: =COUNTIFS(CATALOGUE!$K$2:$K$207,A58,CATALOGUE!$O$2:$O$207,"Include") -> 0 | D58: =COUNTIFS(CATALOGUE!$K$2:$K$207,A58,CATALOGUE!$O$2:$O$207,"Later") -> 0 | E58: =COUNTIFS(CATALOGUE!$K$2:$K$207,A58,CATALOGUE!$O$2:$O$207,"Skip") -> 0
A59: Listed by API – history not checked | B59: =COUNTIF(CATALOGUE!$K$2:$K$207,A59) -> 11 | C59: =COUNTIFS(CATALOGUE!$K$2:$K$207,A59,CATALOGUE!$O$2:$O$207,"Include") -> 0 | D59: =COUNTIFS(CATALOGUE!$K$2:$K$207,A59,CATALOGUE!$O$2:$O$207,"Later") -> 0 | E59: =COUNTIFS(CATALOGUE!$K$2:$K$207,A59,CATALOGUE!$O$2:$O$207,"Skip") -> 0
A60: Not yet tested | B60: =COUNTIF(CATALOGUE!$K$2:$K$207,A60) -> 109 | C60: =COUNTIFS(CATALOGUE!$K$2:$K$207,A60,CATALOGUE!$O$2:$O$207,"Include") -> 0 | D60: =COUNTIFS(CATALOGUE!$K$2:$K$207,A60,CATALOGUE!$O$2:$O$207,"Later") -> 0 | E60: =COUNTIFS(CATALOGUE!$K$2:$K$207,A60,CATALOGUE!$O$2:$O$207,"Skip") -> 0
A61: Partly verified | B61: =COUNTIF(CATALOGUE!$K$2:$K$207,A61) -> 3 | C61: =COUNTIFS(CATALOGUE!$K$2:$K$207,A61,CATALOGUE!$O$2:$O$207,"Include") -> 0 | D61: =COUNTIFS(CATALOGUE!$K$2:$K$207,A61,CATALOGUE!$O$2:$O$207,"Later") -> 0 | E61: =COUNTIFS(CATALOGUE!$K$2:$K$207,A61,CATALOGUE!$O$2:$O$207,"Skip") -> 0
A62: Verified by your test | B62: =COUNTIF(CATALOGUE!$K$2:$K$207,A62) -> 54 | C62: =COUNTIFS(CATALOGUE!$K$2:$K$207,A62,CATALOGUE!$O$2:$O$207,"Include") -> 0 | D62: =COUNTIFS(CATALOGUE!$K$2:$K$207,A62,CATALOGUE!$O$2:$O$207,"Later") -> 0 | E62: =COUNTIFS(CATALOGUE!$K$2:$K$207,A62,CATALOGUE!$O$2:$O$207,"Skip") -> 0
A63: Total | B63: =SUM(B57:B62) -> 206 | C63: =SUM(C57:C62) -> 0 | D63: =SUM(D57:D62) -> 0 | E63: =SUM(E57:E62) -> 0

Sheet CATALOGUE
A1: ID | B1: Theme | C1: Indicator (family) | D1: Key breakdowns | E1: Frequency | F1: Unit | G1: Source agency | H1: Access method | I1: Access detail | J1: History | K1: Verification | L1: Priority | M1: Build tier | N1: Notes | O1: Your decision | P1: Team notes
A2: 01-001 | B2: 01 National Accounts | C2: GDP at current & constant prices | D2: Annual, quarterly; estimate stage (advance/provisional/revised) | E2: Q, A | F2: ₹ crore | G2: MoSPI – NSO | H2: API – official package | I2: esankhyiki NAS (codes 1–22), base 2022-23 + 2011-12 | J2: Base 2011-12: FY2011-12→FY2025-26 (annual & quarterly). Base 2022-23: FY2022-23→FY2025-26 annual, quarterly to FY2026-27 Q1 | K2: Verified by your test | L2: P1 | M2: T1 | N2: 2022-23 back series (history on new base) not yet released – your test returned no data; expected by Dec 2026
A3: 01-002 | B3: 01 National Accounts | C3: Gross Value Added by industry | D3: 8 industries, 18 sub-industries | E3: Q, A | F3: ₹ crore | G3: MoSPI – NSO | H3: API – official package | I3: NAS indicator_code 1 | J3: Base 2011-12: FY2011-12→FY2025-26 (annual & quarterly). Base 2022-23: FY2022-23→FY2025-26 annual, quarterly to FY2026-27 Q1 | K3: Verified by your test | L3: P1 | M3: T1 | N3: Your GDP sample confirmed 15 industry and 18 sub-industry labels
A4: 01-003 | B4: 01 National Accounts | C4: GVA by institutional sector | D4: Public/private non-financial corps, financial corps, government, households (7) | E4: A | F4: ₹ crore | G4: MoSPI – NSO | H4: API – official package | I4: NAS indicator_code 1 (institutional_sector field) | J4: Annual only (per sample) | K4: Verified by your test | L4: P2 | M4: T1
A5: 01-004 | B5: 01 National Accounts | C5: Private Final Consumption Expenditure (PFCE) | D5: By purpose (annual) | E5: Q, A | F5: ₹ crore | G5: MoSPI – NSO | H5: API – official package | I5: NAS (code to map once list endpoint recovers) | J5: Base 2011-12: FY2011-12→FY2025-26 (annual & quarterly). Base 2022-23: FY2022-23→FY2025-26 annual, quarterly to FY2026-27 Q1 | K5: Code verified, name to map | L5: P1 | M5: T1 | N5: NAS indicator-list endpoint was returning HTTP 500 during your test
A6: 01-005 | B6: 01 National Accounts | C6: Government Final Consumption Expenditure (GFCE) | E6: Q, A | F6: ₹ crore | G6: MoSPI – NSO | H6: API – official package | I6: NAS (code to map) | J6: Base 2011-12: FY2011-12→FY2025-26 (annual & quarterly). Base 2022-23: FY2022-23→FY2025-26 annual, quarterly to FY2026-27 Q1 | K6: Code verified, name to map | L6: P1 | M6: T1
A7: 01-006 | B7: 01 National Accounts | C7: Gross Fixed Capital Formation (GFCF) | D7: By asset / institutional sector (annual) | E7: Q, A | F7: ₹ crore | G7: MoSPI – NSO | H7: API – official package | I7: NAS (code to map) | J7: Base 2011-12: FY2011-12→FY2025-26 (annual & quarterly). Base 2022-23: FY2022-23→FY2025-26 annual, quarterly to FY2026-27 Q1 | K7: Code verified, name to map | L7: P1 | M7: T1
A8: 01-007 | B8: 01 National Accounts | C8: Exports & imports of goods and services (NA basis) | E8: Q, A | F8: ₹ crore | G8: MoSPI – NSO | H8: API – official package | I8: NAS (code to map) | J8: Base 2011-12: FY2011-12→FY2025-26 (annual & quarterly). Base 2022-23: FY2022-23→FY2025-26 annual, quarterly to FY2026-27 Q1 | K8: Code verified, name to map | L8: P2 | M8: T1
A9: 01-008 | B9: 01 National Accounts | C9: Change in stocks & valuables | E9: A | F9: ₹ crore | G9: MoSPI – NSO | H9: API – official package | I9: NAS (code to map) | J9: Annual | K9: Code verified, name to map | L9: P3 | M9: T1
A10: 01-009 | B10: 01 National Accounts | C10: Gross / Net National Income (GNI, NNI) | E10: A | F10: ₹ crore | G10: MoSPI – NSO | H10: API – official package | I10: NAS (code to map) | J10: Annual | K10: Code verified, name to map | L10: P2 | M10: T1
A11: 01-010 | B11: 01 National Accounts | C11: Per capita Net National Income | E11: A | F11: ₹ | G11: MoSPI – NSO | H11: API – official package | I11: NAS (code to map) | J11: Annual | K11: Code verified, name to map | L11: P2 | M11: T1
A12: 01-011 | B12: 01 National Accounts | C12: Gross Domestic Saving & saving rate | D12: By institutional sector | E12: A | F12: ₹ crore, % of GDP | G12: MoSPI – NSO | H12: API – official package | I12: NAS (code to map) | J12: Annual | K12: Code verified, name to map | L12: P2 | M12: T1
A13: 01-012 | B13: 01 National Accounts | C13: Gross Capital Formation by industry / sector | E13: A | F13: ₹ crore | G13: MoSPI – NSO | H13: API – official package | I13: NAS (code to map) | J13: Annual | K13: Code verified, name to map | L13: P3 | M13: T1
A14: 01-013 | B14: 01 National Accounts | C14: Consumption of fixed capital | E14: A | F14: ₹ crore | G14: MoSPI – NSO | H14: API – official package | I14: NAS (code to map) | J14: Annual | K14: Code verified, name to map | L14: P3 | M14: T1
A15: 01-014 | B15: 01 National Accounts | C15: GDP deflator | D15: Implicit price deflator | E15: Q, A | F15: Index | G15: Computed from NAS | H15: Derived (computed) | I15: current ÷ constant price GDP | J15: Depends on inputs | K15: Depends on inputs | L15: P2 | M15: T1
A16: 02-001 | B16: 02 Prices & Inflation | C16: CPI (base 2024) – All-India general index & inflation | D16: Rural / Urban / Combined | E16: M | F16: Index; % YoY | G16: MoSPI – NSO | H16: API – official package | I16: CPI base_year=2024 (API returns index AND inflation) | J16: New series live; your sample holds Jul-2026 | K16: Verified by your test | L16: P1 | M16: T1 | N16: Launched Feb 2026
A17: 02-002 | B17: 02 Prices & Inflation | C17: CPI (2024) by division | D17: 13 divisions (food & beverages, housing, transport…) × sector | E17: M | F17: Index; % YoY | G17: MoSPI – NSO | H17: API – official package | I17: CPI level=Group | J17: Same as above | K17: Verified by your test | L17: P1 | M17: T1
A18: 02-003 | B18: 02 Prices & Inflation | C18: CPI (2024) groups, classes, sub-classes | D18: 43 groups, 92 classes, 162 sub-classes | E18: M | F18: Index; % YoY | G18: MoSPI – NSO | H18: API – official package | I18: CPI level=Group/Item | J18: Same as above | K18: Verified by your test | L18: P2 | M18: T1 | N18: Counts from your sample
A19: 02-004 | B19: 02 Prices & Inflation | C19: CPI (2024) items | D19: 358 items (667 codes) × sector | E19: M | F19: Index; % YoY | G19: MoSPI – NSO | H19: API – official package | I19: CPI level=Item | J19: Same as above | K19: Verified by your test | L19: P2 | M19: T1 | N19: STORAGE: one month at full state×item detail exceeded 5,000 rows – decide detail level
A20: 02-005 | B20: 02 Prices & Inflation | C20: CPI (2024) state-wise | D20: 36 States/UTs × sector × division | E20: M | F20: Index; % YoY | G20: MoSPI – NSO | H20: API – official package | I20: CPI state filter | J20: Same as above | K20: Verified by your test | L20: P2 | M20: T1
A21: 02-006 | B21: 02 Prices & Inflation | C21: CPI (base 2012) historical series | D21: Groups & items; states; sectors | E21: M | F21: Index; % YoY | G21: MoSPI – NSO | H21: API – official package | I21: CPI base_year=2012 | J21: Groups 2011→2025; items 2014→2025 | K21: Verified by your test | L21: P1 | M21: T1 | N21: Needed for long history; join to 2024 base only via official linking factor
A22: 02-007 | B22: 02 Prices & Inflation | C22: CPI (base 2010) older series | E22: M | F22: Index | G22: MoSPI – NSO | H22: API – official package | I22: CPI base_year=2010 | J22: 2011→2014 | K22: Verified by your test | L22: P3 | M22: T1
A23: 02-008 | B23: 02 Prices & Inflation | C23: CPI food & beverages inflation | D23: Rural / Urban / Combined | E23: M | F23: % YoY | G23: MoSPI – NSO | H23: API – official package | I23: CPI division 01 | J23: As CPI 2024 + 2012 | K23: Verified by your test | L23: P1 | M23: T1
A24: 02-009 | B24: 02 Prices & Inflation | C24: Core CPI (ex food & fuel) | E24: M | F24: % YoY | G24: Computed from CPI weights | H24: Derived (computed) | I24: Exclusion index from division indices + weights | J24: Depends on inputs | K24: Depends on inputs | L24: P1 | M24: T1 | N24: Not published officially – compute consistently
A25: 02-010 | B25: 02 Prices & Inflation | C25: CPI for Agricultural & Rural Labourers (CPI-AL / RL) | D25: General & group index; states | E25: M | F25: Index | G25: Labour Bureau via MoSPI | H25: API – official package | I25: CPIALRL indicator 1, 2 | J25: Base 1986-87 & 2019; years 1999-2000→2026 | K25: Verified by your test | L25: P2 | M25: T1
A26: 02-011 | B26: 02 Prices & Inflation | C26: CPI for Industrial Workers (CPI-IW, base 2016) | D26: 88 centres, groups | E26: M | F26: Index | G26: Labour Bureau | H26: PDF parse | I26: labourbureau.gov.in monthly release | J26: Expected long (verify) | K26: Not yet tested | L26: P2 | M26: T3
A27: 02-012 | B27: 02 Prices & Inflation | C27: WPI (base 2022-23) headline & inflation | D27: Primary, Fuel & power, Manufactured | E27: M | F27: Index; % YoY | G27: OEA (DPIIT) via MoSPI | H27: API – official package | I27: WPI base_year=2022-23 | J27: 2023→2026 | K27: Verified by your test | L27: P1 | M27: T1 | N27: New series from Apr-2023
A28: 02-013 | B28: 02 Prices & Inflation | C28: WPI commodity-level indices | D28: All commodities × major groups | E28: M | F28: Index | G28: OEA (DPIIT) via MoSPI | H28: API – official package | I28: WPI series filter | J28: 2023→2026 | K28: Verified by your test | L28: P2 | M28: T1
A29: 02-014 | B29: 02 Prices & Inflation | C29: WPI (base 2011-12) historical | E29: M | F29: Index; % YoY | G29: OEA (DPIIT) via MoSPI | H29: API – official package | I29: WPI base_year=2011-12 | J29: 2012→2026 | K29: Verified by your test | L29: P1 | M29: T1 | N29: Link to new base with OEA linking factor
A30: 02-015 | B30: 02 Prices & Inflation | C30: WPI (base 2004-05, 1993-94) older series | E30: M | F30: Index | G30: OEA (DPIIT) via MoSPI | H30: API – official package | I30: WPI older base_year | J30: 1993-94 base: 1994→2010 · 2004-05 base: 2005→2017 | K30: Verified by your test | L30: P3 | M30: T1 | N30: Enables history back to the 1990s
A31: 02-016 | B31: 02 Prices & Inflation | C31: WPI Food Index | E31: M | F31: Index; % YoY | G31: OEA (DPIIT) | H31: Download (Excel/CSV) | I31: eaindustry.nic.in | J31: Expected (verify) | K31: Not yet tested | L31: P2 | M31: T2
A32: 02-017 | B32: 02 Prices & Inflation | C32: Producer Price Index (PPI) – new | D32: Output PPI, input PPI (trial), services PPI (quarterly) | E32: M, Q | F32: Index | G32: OEA (DPIIT) | H32: Download (Excel/CSV) | I32: eaindustry.nic.in | J32: Short (launched 2026) | K32: Not yet tested | L32: P2 | M32: T2
A33: 02-018 | B33: 02 Prices & Inflation | C33: Retail & wholesale prices of 22 essential commodities | D33: ~550 centres | E33: D | F33: ₹/kg, ₹/litre | G33: Dept. of Consumer Affairs – Price Monitoring Cell | H33: Scrape (HTML) | I33: DoCA price monitoring site | J33: Expected long (verify) | K33: Not yet tested | L33: P2 | M33: T3 | N33: Tomato/onion/potato, pulses, edible oils…
A34: 02-019 | B34: 02 Prices & Inflation | C34: Mandi (APMC) prices & arrivals | D34: Commodity × variety × market | E34: D | F34: ₹/quintal | G34: Agmarknet via data.gov.in | H34: API – free key | I34: Resources 9ef84268-d588-465a-a308-a864a43d0070 (daily); variety-wise 35985678-… (full ID to copy) | J34: API returns the current day only (6,612 rows on 11-Sep-2026) – daily capture builds history | K34: Verified by your test | L34: P2 | M34: T1b
A35: 02-020 | B35: 02 Prices & Inflation | C35: Retail petrol, diesel, LPG, ATF prices | D35: Metros | E35: D, M | F35: ₹/litre, ₹/cylinder | G35: PPAC / oil marketing companies | H35: Download (Excel/CSV) | I35: ppac.gov.in price data | J35: Expected long (verify) | K35: Not yet tested | L35: P2 | M35: T2
A36: 02-021 | B36: 02 Prices & Inflation | C36: Indian basket crude oil price | E36: D | F36: US$/bbl | G36: PPAC | H36: Download (Excel/CSV) | I36: ppac.gov.in | J36: Expected long (verify) | K36: Not yet tested | L36: P1 | M36: T2
A37: 02-022 | B37: 02 Prices & Inflation | C37: Gold & silver domestic prices | E37: D | F37: ₹/10g, ₹/kg | G37: IBJA | H37: Scrape (HTML) | I37: ibjarates.com | J37: Verify | K37: Not yet tested | L37: P3 | M37: T3 | N37: Fallback: Yahoo GC=F / SI=F × USD/INR
A38: 03-001 | B38: 03 Industry & Production | C38: IIP (base 2022-23) general index & growth | E38: M | F38: Index; % YoY | G38: MoSPI – NSO | H38: API – official package | I38: IIP base_year=2022-23 Monthly/Annually | J38: Monthly 2023→2026; annual FY2023-24→FY2025-26 | K38: Verified by your test | L38: P1 | M38: T1
A39: 03-002 | B39: 03 Industry & Production | C39: IIP sectoral | D39: Mining, Manufacturing, Electricity | E39: M | F39: Index; % YoY | G39: MoSPI – NSO | H39: API – official package | I39: IIP | J39: As above | K39: Verified by your test | L39: P1 | M39: T1
A40: 03-003 | B40: 03 Industry & Production | C40: IIP use-based | D40: Primary, Capital, Intermediate, Infra/Construction, Consumer durables, Consumer non-durables | E40: M | F40: Index; % YoY | G40: MoSPI – NSO | H40: API – official package | I40: IIP | J40: As above | K40: Verified by your test | L40: P1 | M40: T1
A41: 03-004 | B41: 03 Industry & Production | C41: IIP manufacturing by industry (NIC 2-digit) | D41: ~23 industries | E41: M | F41: Index | G41: MoSPI – NSO | H41: API – official package | I41: IIP | J41: As above | K41: Verified by your test | L41: P2 | M41: T1
A42: 03-005 | B42: 03 Industry & Production | C42: IIP (base 2011-12) historical | D42: Same breakdowns | E42: M | F42: Index | G42: MoSPI – NSO | H42: API – official package | I42: IIP base_year=2011-12 | J42: Monthly 2012→2026; annual FY2012-13→FY2025-26 | K42: Verified by your test | L42: P1 | M42: T1
A43: 03-006 | B43: 03 Industry & Production | C43: IIP (base 2004-05, 1993-94) older series | E43: M | F43: Index | G43: MoSPI – NSO | H43: API – official package | I43: IIP older base_year | J43: 1993-94 base: 1994→2011 · 2004-05 base: 2005→2017 | K43: Verified by your test | L43: P3 | M43: T1 | N43: Enables history back to the 1990s
A44: 03-007 | B44: 03 Industry & Production | C44: Index of Eight Core Industries (base 2022-23) | D44: Coal, crude oil, natural gas, refinery products, fertilisers, steel, cement, electricity | E44: M | F44: Index; % YoY | G44: OEA (DPIIT) | H44: Download (Excel/CSV) | I44: eaindustry.nic.in | J44: Expected long (verify) | K44: Not yet tested | L44: P1 | M44: T2 | N44: ~40% weight in IIP; released ~2 weeks earlier
A45: 03-008 | B45: 03 Industry & Production | C45: Index of Services Production (ISP, trial) | D45: Services sub-sectors | E45: M, A | F45: Index | G45: MoSPI – NSO | H45: API – official package | I45: ISP frequency_code 1/2 | J45: Yearly 2025-26; monthly 2025-26→2026-27 (new, short) | K45: Verified by your test | L45: P2 | M45: T1
A46: 03-009 | B46: 03 Industry & Production | C46: Annual Survey of Industries (ASI) | D46: Factories, output, GVA, invested capital, employment, wages, profits × NIC × state | E46: A | F46: ₹ lakh, number | G46: MoSPI – NSO | H46: API – official package | I46: ASI classification_year 2008 / 2004 | J46: NIC-2008: 2008-09→2023-24; NIC-2004: 2004-05→2007-08 | K46: Verified by your test | L46: P2 | M46: T1
A47: 03-010 | B47: 03 Industry & Production | C47: Unincorporated non-agri enterprises (ASUSE) | D47: Establishments, workers, GVA × state × activity | E47: A, Q | F47: Number, ₹ | G47: MoSPI – NSO | H47: API – official package | I47: ASUSE (50 indicators) | J47: Listed; to verify | K47: Listed by API – history not checked | L47: P3 | M47: T1
A48: 03-011 | B48: 03 Industry & Production | C48: PMI – Manufacturing, Services, Composite | E48: M | F48: Diffusion index | G48: HSBC / S&P Global | H48: Paid / licensed | I48: Headline figure from public press release only | J48: Licensed | K48: Not yet tested | L48: P2 | M48: T4 | N48: Do not scrape full data – licence required
A49: 03-012 | B49: 03 Industry & Production | C49: Vehicle registrations | D49: Vehicle class × fuel type (incl. EV) × state × RTO | E49: D, M | F49: Number | G49: MoRTH – Vahan dashboard | H49: Scrape (HTML) | I49: vahan.parivahan.gov.in (JavaScript site – Playwright) | J49: Expected long (verify) | K49: Not yet tested | L49: P1 | M49: T3 | N49: Best high-frequency consumption proxy
A50: 03-013 | B50: 03 Industry & Production | C50: Automobile production & domestic sales | D50: PV, 2W, 3W, CV | E50: M | F50: Units | G50: SIAM / company releases | H50: Scrape (HTML) | I50: Monthly press releases (detailed tables are paid) | J50: Verify | K50: Not yet tested | L50: P2 | M50: T3
A51: 03-014 | B51: 03 Industry & Production | C51: Tractor sales | E51: M | F51: Units | G51: Company releases | H51: Scrape (HTML) | I51: Mahindra/Escorts/Sonalika monthly releases | J51: Verify | K51: Not yet tested | L51: P3 | M51: T3 | N51: Rural demand proxy
A52: 03-015 | B52: 03 Industry & Production | C52: Steel production & consumption | D52: Crude steel, finished steel | E52: M | F52: Million tonnes | G52: Ministry of Steel / JPC | H52: PDF parse | I52: Monthly reports | J52: Verify | K52: Not yet tested | L52: P2 | M52: T3
A53: 03-016 | B53: 03 Industry & Production | C53: Coal production & despatch | D53: CIL, SCCL, captive | E53: M | F53: Million tonnes | G53: Ministry of Coal | H53: PDF parse | I53: Monthly press / dashboard | J53: Verify | K53: Not yet tested | L53: P2 | M53: T3
A54: 03-017 | B54: 03 Industry & Production | C54: Fertiliser production & sales | D54: Urea, DAP, MOP, NPK | E54: M | F54: Lakh tonnes | G54: Dept. of Fertilizers | H54: Download (Excel/CSV) | I54: fert.nic.in / data.gov.in | J54: Verify | K54: Not yet tested | L54: P3 | M54: T2
A55: 04-001 | B55: 04 Services & High-Frequency Activity | C55: GST e-way bills generated | D55: Intra/inter-state; state-wise | E55: M | F55: Number, ₹ value | G55: GSTN | H55: Scrape (HTML) | I55: E-way bill portal statistics | J55: Verify | K55: Not yet tested | L55: P1 | M55: T3 | N55: Leading indicator of goods movement
A56: 04-002 | B56: 04 Services & High-Frequency Activity | C56: UPI transactions | D56: Volume, value | E56: M (daily also) | F56: Crore txns, ₹ lakh crore | G56: NPCI | H56: Scrape (HTML) | I56: npci.org.in product statistics | J56: Since 2016 (verify) | K56: Not yet tested | L56: P1 | M56: T3
A57: 04-003 | B57: 04 Services & High-Frequency Activity | C57: IMPS, NEFT, RTGS, AePS, card & ATM transactions | D57: Volume, value | E57: M | F57: Number, ₹ | G57: RBI – payment system indicators | H57: Download (Excel/CSV) | I57: RBI DBIE / monthly bulletin | J57: Verify | K57: Not yet tested | L57: P2 | M57: T2
A58: 04-004 | B58: 04 Services & High-Frequency Activity | C58: Credit & debit card spends and cards outstanding | D58: By bank | E58: M | F58: ₹, number | G58: RBI – ATM/POS/card statistics | H58: Download (Excel/CSV) | I58: RBI monthly bank-wise statistics | J58: Verify | K58: Not yet tested | L58: P2 | M58: T2
A59: 04-005 | B59: 04 Services & High-Frequency Activity | C59: FASTag / NETC toll transactions | D59: Volume, value | E59: M | F59: Number, ₹ | G59: NPCI | H59: Scrape (HTML) | I59: npci.org.in NETC statistics | J59: Verify | K59: Not yet tested | L59: P2 | M59: T3 | N59: Road-freight proxy
A60: 04-006 | B60: 04 Services & High-Frequency Activity | C60: Railway freight loading & earnings | D60: Commodity-wise | E60: M | F60: Million tonnes, ₹ | G60: Ministry of Railways | H60: PDF parse | I60: Monthly press release | J60: Verify | K60: Not yet tested | L60: P1 | M60: T3
A61: 04-007 | B61: 04 Services & High-Frequency Activity | C61: Major port cargo traffic | D61: Port × commodity | E61: M | F61: Million tonnes | G61: Indian Ports Association | H61: Download (Excel/CSV) | I61: ipa.nic.in | J61: Verify | K61: Not yet tested | L61: P2 | M61: T2
A62: 04-008 | B62: 04 Services & High-Frequency Activity | C62: Domestic air passenger traffic | D62: By airline | E62: M | F62: Lakh passengers | G62: DGCA | H62: PDF parse | I62: Monthly traffic data | J62: Verify | K62: Not yet tested | L62: P1 | M62: T3
A63: 04-009 | B63: 04 Services & High-Frequency Activity | C63: International air passengers & air cargo | D63: Airport-wise | E63: M | F63: Number, tonnes | G63: Airports Authority of India | H63: Download (Excel/CSV) | I63: aai.aero traffic statistics | J63: Verify | K63: Not yet tested | L63: P3 | M63: T2
A64: 04-010 | B64: 04 Services & High-Frequency Activity | C64: Foreign tourist arrivals & forex earnings from tourism | E64: M | F64: Number, ₹ crore | G64: Ministry of Tourism | H64: PDF parse | I64: Monthly release | J64: Verify | K64: Not yet tested | L64: P3 | M64: T3
A65: 04-011 | B65: 04 Services & High-Frequency Activity | C65: Telecom subscribers (wireless, broadband) | D65: Operator × circle | E65: M | F65: Million | G65: TRAI | H65: PDF parse | I65: Monthly subscription data | J65: Verify | K65: Not yet tested | L65: P3 | M65: T3
A66: 05-001 | B66: 05 Labour & Employment | C66: Unemployment Rate (PLFS) | D66: State × gender × age × rural/urban; CWS & usual status | E66: M, Q, A | F66: % | G66: MoSPI – NSO | H66: API – official package | I66: PLFS indicator 3 (freq 1/2/3; needs year_type_code) | J66: Annual 2017-18→2025 · quarterly 2018→2026 · monthly 2025→2026 | K66: Verified by your test | L66: P1 | M66: T1 | N66: Monthly estimates are new (from 2025)
A67: 05-002 | B67: 05 Labour & Employment | C67: Labour Force Participation Rate (PLFS) | D67: As above | E67: M, Q, A | F67: % | G67: MoSPI – NSO | H67: API – official package | I67: PLFS indicator 1 | J67: Annual 2017-18→2025 · quarterly 2018→2026 · monthly 2025→2026 | K67: Verified by your test | L67: P1 | M67: T1
A68: 05-003 | B68: 05 Labour & Employment | C68: Worker Population Ratio (PLFS) | D68: As above | E68: M, Q, A | F68: % | G68: MoSPI – NSO | H68: API – official package | I68: PLFS indicator 2 | J68: Annual 2017-18→2025 · quarterly 2018→2026 · monthly 2025→2026 | K68: Verified by your test | L68: P1 | M68: T1
A69: 05-004 | B69: 05 Labour & Employment | C69: Distribution of workers by status & industry | D69: Self-employed / regular / casual; industry | E69: Q, A | F69: % | G69: MoSPI – NSO | H69: API – official package | I69: PLFS indicator 4 | J69: Annual 2017-18→2025 · quarterly 2018→2026 | K69: Verified by your test | L69: P2 | M69: T1
A70: 05-005 | B70: 05 Labour & Employment | C70: Regular employees with job contract / paid leave / social security | E70: A | F70: % | G70: MoSPI – NSO | H70: API – official package | I70: PLFS indicator 5 | J70: Annual 2017-18→2023-24 | K70: Verified by your test | L70: P3 | M70: T1 | N70: Job-quality measure
A71: 05-006 | B71: 05 Labour & Employment | C71: Earnings: regular wage, casual daily wage, self-employment | D71: Gender × sector × state | E71: A | F71: ₹ | G71: MoSPI – NSO | H71: API – official package | I71: PLFS indicators 6, 7, 8 | J71: Annual 2017-18→2025 | K71: Verified by your test | L71: P2 | M71: T1
A72: 05-007 | B72: 05 Labour & Employment | C72: EPFO net payroll additions | D72: Age group, state, industry | E72: M | F72: Number | G72: EPFO / MoSPI payroll reporting | H72: PDF parse | I72: Monthly payroll release | J72: Verify | K72: Not yet tested | L72: P1 | M72: T3 | N72: Formal job creation proxy; revised often
A73: 05-008 | B73: 05 Labour & Employment | C73: ESIC & NPS new subscribers | E73: M | F73: Number | G73: MoSPI payroll reporting | H73: PDF parse | I73: Monthly payroll release | J73: Verify | K73: Not yet tested | L73: P2 | M73: T3
A74: 05-009 | B74: 05 Labour & Employment | C74: MGNREGA work demand & person-days | D74: State, district | E74: D, M | F74: Households, person-days | G74: Ministry of Rural Development | H74: Scrape (HTML) | I74: nrega.nic.in reports / data.gov.in | J74: Verify | K74: Not yet tested | L74: P1 | M74: T3 | N74: Rural distress proxy
A75: 05-010 | B75: 05 Labour & Employment | C75: Rural wage rates | D75: Agricultural & non-agricultural occupations × state | E75: M | F75: ₹/day | G75: Labour Bureau | H75: PDF parse | I75: Wage Rates in Rural India | J75: Verify | K75: Not yet tested | L75: P3 | M75: T3
A76: 06-001 | B76: 06 Money, Banking & Credit | C76: Policy rates: repo, SDF, MSF, bank rate, CRR, SLR | E76: Event | F76: % | G76: RBI | H76: Scrape (HTML) | I76: RBI current rates / MPC statements | J76: Long | K76: Not yet tested | L76: P1 | M76: T2
A77: 06-002 | B77: 06 Money, Banking & Credit | C77: Weighted Average Call Rate (WACR) & money-market rates | D77: Call, TREPS, market repo | E77: D | F77: % | G77: RBI / CCIL | H77: Download (Excel/CSV) | I77: RBI DBIE / money market operations release | J77: Verify | K77: Not yet tested | L77: P1 | M77: T2
A78: 06-003 | B78: 06 Money, Banking & Credit | C78: System liquidity (LAF net injection/absorption) | E78: D | F78: ₹ crore | G78: RBI | H78: Download (Excel/CSV) | I78: Money market operations press release | J78: Verify | K78: Not yet tested | L78: P1 | M78: T2
A79: 06-004 | B79: 06 Money, Banking & Credit | C79: Treasury bill yields (91/182/364-day) | D79: Auction cut-offs; secondary | E79: W, D | F79: % | G79: RBI / FBIL | H79: Download (Excel/CSV) | I79: Auction results; FBIL T-bill curve | J79: Verify | K79: Not yet tested | L79: P1 | M79: T2
A80: 06-005 | B80: 06 Money, Banking & Credit | C80: Commercial paper & certificate of deposit rates, issuance | E80: Fortnightly | F80: %, ₹ crore | G80: RBI | H80: Download (Excel/CSV) | I80: RBI DBIE | J80: Verify | K80: Not yet tested | L80: P3 | M80: T2
A81: 06-006 | B81: 06 Money, Banking & Credit | C81: Reserve money & currency in circulation | E81: W | F81: ₹ crore | G81: RBI – Weekly Statistical Supplement | H81: Download (Excel/CSV) | I81: RBI DBIE | J81: Long | K81: Not yet tested | L81: P2 | M81: T2
A82: 06-007 | B82: 06 Money, Banking & Credit | C82: Money supply (M1, M3) & components | E82: Fortnightly | F82: ₹ crore; % YoY | G82: RBI | H82: Download (Excel/CSV) | I82: RBI DBIE | J82: Long | K82: Not yet tested | L82: P1 | M82: T2
A83: 06-008 | B83: 06 Money, Banking & Credit | C83: Scheduled commercial bank deposits & credit | D83: Aggregate, time vs demand deposits | E83: Fortnightly | F83: ₹ crore; % YoY | G83: RBI | H83: Download (Excel/CSV) | I83: RBI DBIE | J83: Long | K83: Not yet tested | L83: P1 | M83: T2
A84: 06-009 | B84: 06 Money, Banking & Credit | C84: Sectoral deployment of bank credit | D84: Agriculture, industry (by size & industry), services, personal loans (housing, vehicle, cards, gold, education) | E84: M | F84: ₹ crore; % YoY | G84: RBI | H84: Download (Excel/CSV) | I84: RBI DBIE / monthly release | J84: Verify | K84: Not yet tested | L84: P1 | M84: T2
A85: 06-010 | B85: 06 Money, Banking & Credit | C85: Weighted average lending & deposit rates (WALR, WADTDR) | D85: Fresh vs outstanding | E85: M | F85: % | G85: RBI | H85: Download (Excel/CSV) | I85: RBI DBIE | J85: Verify | K85: Not yet tested | L85: P1 | M85: T2 | N85: Monetary transmission
A86: 06-011 | B86: 06 Money, Banking & Credit | C86: MCLR & EBLR (median) | E86: M | F86: % | G86: RBI | H86: Download (Excel/CSV) | I86: RBI DBIE | J86: Verify | K86: Not yet tested | L86: P2 | M86: T2
A87: 06-012 | B87: 06 Money, Banking & Credit | C87: Bank asset quality: GNPA, NNPA, CRAR, SMA | D87: Bank group | E87: Half-yearly | F87: % | G87: RBI – Financial Stability Report | H87: PDF parse | I87: FSR tables | J87: Verify | K87: Not yet tested | L87: P2 | M87: T3
A88: 06-013 | B88: 06 Money, Banking & Credit | C88: NBFC & HFC credit | E88: Q | F88: ₹ crore | G88: RBI | H88: Download (Excel/CSV) | I88: RBI DBIE / FSR | J88: Verify | K88: Not yet tested | L88: P3 | M88: T2
A89: 06-014 | B89: 06 Money, Banking & Credit | C89: Household financial savings & liabilities | D89: Deposits, MFs, insurance, borrowings | E89: A, Q | F89: ₹ crore; % GDP | G89: RBI – Bulletin | H89: Download (Excel/CSV) | I89: RBI Bulletin tables | J89: Verify | K89: Not yet tested | L89: P2 | M89: T2
A90: 06-015 | B90: 06 Money, Banking & Credit | C90: Bank credit & deposits by state and district | D90: Population group (rural/urban/metro) | E90: Q | F90: ₹ crore | G90: RBI – BSR | H90: Download (Excel/CSV) | I90: RBI DBIE quarterly BSR | J90: Verify | K90: Not yet tested | L90: P3 | M90: T2
A91: 06-016 | B91: 06 Money, Banking & Credit | C91: Small savings interest rates | D91: PPF, NSC, SSY… | E91: Q | F91: % | G91: Ministry of Finance | H91: Scrape (HTML) | I91: Quarterly notification | J91: Verify | K91: Not yet tested | L91: P3 | M91: T3
A92: 07-001 | B92: 07 Financial Markets | C92: Nifty 50 & Sensex (OHLC, volume) | E92: D | F92: Index points | G92: NSE, BSE via Yahoo | H92: API – unofficial | I92: yfinance ^NSEI, ^BSESN | J92: Sensex 1997-07-01→ · Nifty 2007-09-17→ | K92: Verified by your test | L92: P1 | M92: T1b | N92: Yahoo terms: personal/internal use; don't redistribute
A93: 07-002 | B93: 07 Financial Markets | C93: Nifty sectoral indices | D93: Bank, IT, Auto, FMCG, Pharma, Metal, Realty, Energy, PSU Bank, Infra, Media | E93: D | F93: Index points | G93: NSE via Yahoo | H93: API – unofficial | I93: yfinance ^NSEBANK, ^CNXIT … | J93: Bank & IT 2007-09→ · Realty & Infra 2010-07→ · others 2011→ · recent gaps in some indices | K93: Verified by your test | L93: P2 | M93: T1b
A94: 07-003 | B94: 07 Financial Markets | C94: Broad-market indices | D94: Nifty 500, Midcap 50, Smallcap 100 | E94: D | F94: Index points | G94: NSE via Yahoo | H94: API – unofficial | I94: yfinance ^CRSLDX, ^NSEMDCP50, ^CNXSC | J94: Nifty 500 2005-09→ · Midcap 50 2007-09→ · Smallcap 100 (^CNXSC) no longer works | K94: Verified by your test | L94: P2 | M94: T1b
A95: 07-004 | B95: 07 Financial Markets | C95: India VIX | E95: D | F95: Index | G95: NSE via Yahoo | H95: API – unofficial | I95: yfinance ^INDIAVIX | J95: 2008-03-03→ | K95: Verified by your test | L95: P1 | M95: T1b
A96: 07-005 | B96: 07 Financial Markets | C96: Market valuation: Nifty P/E, P/B, dividend yield | E96: D | F96: Ratio | G96: NSE | H96: Scrape (HTML) | I96: NSE archives (blocks automated access – hard) | J96: Verify | K96: Not yet tested | L96: P2 | M96: T3
A97: 07-006 | B97: 07 Financial Markets | C97: 10-year G-sec benchmark yield | E97: D | F97: % | G97: FBIL / CCIL | H97: Download (Excel/CSV) | I97: FBIL G-sec valuation; CCIL NDS-OM | J97: Verify | K97: Not yet tested | L97: P1 | M97: T2 | N97: Not available on Yahoo
A98: 07-007 | B98: 07 Financial Markets | C98: G-sec yield curve (par & zero-coupon, 1–40Y) | E98: D | F98: % | G98: FBIL | H98: Download (Excel/CSV) | I98: fbil.org.in | J98: Verify | K98: Not yet tested | L98: P2 | M98: T2
A99: 07-008 | B99: 07 Financial Markets | C99: Overnight & term benchmarks (MIBOR, TREPS) | E99: D | F99: % | G99: FBIL / CCIL | H99: Download (Excel/CSV) | I99: fbil.org.in, ccilindia.com | J99: Verify | K99: Not yet tested | L99: P2 | M99: T2
A100: 07-009 | B100: 07 Financial Markets | C100: SDL cut-off yields & spreads over G-sec | D100: State-wise | E100: W | F100: % | G100: RBI auction results | H100: Scrape (HTML) | I100: Weekly SDL auction press release | J100: Verify | K100: Not yet tested | L100: P3 | M100: T3
...

Sheet MOSPI_VERIFIED
A1: MoSPI API – history coverage from YOUR test runs (02 and 02b, 11-Sep-2026)
A2: Source: output/mospi_history.xlsx. Periods are those the API lists as available. FY = April–March.
A4: Dataset | B4: Probe (base year / frequency) | C4: Period field | D4: No. of periods | E4: Earliest | F4: Latest | G4: Note
A5: CPI | B5: base 2024 | Group | Current | C5: year | D5: 1 | E5: (not listed) | F5: (not listed) | G5: Year list not exposed for 2024 base; your data sample contains 2026 data
A6: CPI | B6: base 2024 | Item | Current | C6: year | D6: 1 | E6: (not listed) | F6: (not listed) | G6: Year list not exposed for 2024 base; your data sample contains 2026 data
A7: CPI | B7: base 2012 | Group | Current | C7: year | D7: 15 | E7: 2011 | F7: 2025
A8: CPI | B8: base 2012 | Item | Current | C8: year | D8: 12 | E8: 2014 | F8: 2025
A9: CPI | B9: base 2024 | Group | Back series | C9: year | D9: 1 | E9: (not listed) | F9: (not listed) | G9: Year list not exposed for 2024 base; your data sample contains 2026 data
A10: WPI | B10: base 2022-23 | C10: year | D10: 4 | E10: 2023 | F10: 2026
A11: WPI | B11: base 2011-12 | C11: year | D11: 15 | E11: 2012 | F11: 2026
A12: IIP | B12: base 2022-23 | Monthly | C12: year | D12: 4 | E12: 2023 | F12: 2026
A13: IIP | B13: base 2022-23 | Annually | C13: financial_year | D13: 3 | E13: 2023-24 | F13: 2025-26
A14: IIP | B14: base 2011-12 | Monthly | C14: year | D14: 15 | E14: 2012 | F14: 2026
A15: IIP | B15: base 2011-12 | Annually | C15: financial_year | D15: 14 | E15: 2012-13 | F15: 2025-26
A16: ASI | B16: NIC classification 2008 | C16: year | D16: 16 | E16: 2008-09 | F16: 2023-24
A17: ASI | B17: NIC classification 2004 | C17: year | D17: 4 | E17: 2004-05 | F17: 2007-08
A18: ISP | B18: frequency Yearly | C18: year | D18: 1 | E18: 2025-26 | F18: 2025-26
A19: ISP | B19: frequency Monthly | C19: year | D19: 2 | E19: 2025-26 | F19: 2026-27
A20: NAS | B20: 1 | base 2022-23 | Annual | C20: year | D20: 4 | E20: 2022-23 | F20: 2025-26
A21: NAS | B21: 1 | base 2022-23 | Quarterly | C21: year | D21: 5 | E21: 2022-23 | F21: 2026-27
... A94: MNRE | B94: 5 Total | C94: year | D94: 7 | E94: 2020 | F94: 2026
A95: PLFS | B95: 1 LFPR (Labour Force Participa | freq 1 | agri/FY year (re-test) | C95: year | D95: 11 | E95: 2017-18 | F95: 2025 | G95: From 02b re-test
A96: PLFS | B96: 1 LFPR (Labour Force Participa | freq 1 | calendar year (re-test) | C96: year | D96: 11 | E96: 2017-18 | F96: 2025 | G96: From 02b re-test
A97: PLFS | B97: 2 WPR (Worker Population Ratio | freq 1 | agri/FY year (re-test) | C97: year | D97: 11 | E97: 2017-18 | F97: 2025 | G97: From 02b re-test
A98: PLFS | B98: 2 WPR (Worker Population Ratio | freq 1 | calendar year (re-test) | C98: year | D98: 11 | E98: 2017-18 | F98: 2025 | G98: From 02b re-test
A99: PLFS | B99: 3 UR (Unemployment Rate, in pe | freq 1 | agri/FY year (re-test) | C99: year | D99: 11 | E99: 2017-18 | F99: 2025 | G99: From 02b re-test
A100: PLFS | B100: 3 UR (Unemployment Rate, in pe | freq 1 | calendar year (re-test) | C100: year | D100: 11 | E100: 2017-18 | F100: 2025 | G100: From 02b re-test
A101: PLFS | B101: 4 Percentage distribution of w | freq 1 | agri/FY year (re-test) | C101: year | D101: 11 | E101: 2017-18 | F101: 2025 | G101: From 02b re-test
A102: PLFS | B102: 4 Percentage distribution of w | freq 1 | calendar year (re-test) | C102: year | D102: 11 | E102: 2017-18 | F102: 2025 | G102: From 02b re-test
A103: PLFS | B103: 5 Percentage of regular wage/ | freq 1 | agri/FY year (re-test) | C103: year | D103: 7 | E103: 2017-18 | F103: 2023-24 | G103: From 02b re-test
A104: PLFS | B104: 5 Percentage of regular wage/ | freq 1 | calendar year (re-test) | C104: year | D104: 7 | E104: 2017-18 | F104: 2023-24 | G104: From 02b re-test
A105: PLFS | B105: 6 Average wage/salary earnings | freq 1 | agri/FY year (re-test) | C105: year | D105: 11 | E105: 2017-18 | F105: 2025 | G105: From 02b re-test
A106: PLFS | B106: 6 Average wage/salary earnings | freq 1 | calendar year (re-test) | C106: year | D106: 11 | E106: 2017-18 | F106: 2025 | G106: From 02b re-test
... A174: CPI | B174: base 2010 | Group | Current (re-test) | C174: year | D174: 4 | E174: 2011 | F174: 2014 | G174: From 02b re-test
A177: Failed probes – why
A178: Dataset | B178: Failed probes | G178: Reason
A179: NAS | B179: 42 | G179: Back series (2022-23 base) not released yet; quarterly not published for some codes – genuine 'no data'
A180: PLFS / RBI / ENERGY | B180: 0 (fixed) | G180: First run lacked required parameters; all 137 re-test probes passed (rows marked 're-test' above)

Sheet NAS_CODES
A1: NAS (GDP) indicator codes 1–22 – availability from your test
A2: Indicator names could not be listed (MoSPI's list endpoint returned HTTP 500). Code 1 = Gross Value Added (confirmed by your sample). Map the rest once the endpoint recovers.
A4: Code | B4: Name | C4: 2022-23 base Annual | D4: 2022-23 base Quarterly | E4: 2011-12 base Annual | F4: 2011-12 base Quarterly | G4: 2022-23 Back series
A5: 1 | B5: Gross Value Added | C5: 2022-23 → 2025-26 | D5: 2022-23 → 2026-27 | E5: 2011-12 → 2025-26 | F5: 2011-12 → 2025-26 | G5: no data
A6: 2 | B6: (to map) | C6: 2022-23 → 2025-26 | D6: 2022-23 → 2026-27 | E6: 2011-12 → 2025-26 | F6: 2011-12 → 2025-26 | G6: no data
A7: 3 | B7: (to map) | C7: 2022-23 → 2024-25 | D7: no data | E7: 2011-12 → 2023-24 | F7: no data | G7: no data
A8: 4 | B8: (to map) | C8: 2022-23 → 2024-25 | D8: no data | E8: 2011-12 → 2023-24 | F8: no data | G8: no data
A9: 5 | B9: (to map) | C9: 2022-23 → 2025-26 | D9: 2022-23 → 2026-27 | E9: 2011-12 → 2025-26 | F9: 2011-12 → 2025-26 | G9: no data
A10: 6 | B10: (to map) | C10: 2022-23 → 2024-25 | D10: no data | E10: 2011-12 → 2023-24 | F10: no data | G10: no data
A11: 7 | B11: (to map) | C11: 2022-23 → 2025-26 | D11: no data | E11: 2011-12 → 2025-26 | F11: no data | G11: no data
A12: 8 | B12: (to map) | C12: 2022-23 → 2024-25 | D12: no data | E12: 2011-12 → 2023-24 | F12: no data | G12: no data
A13: 9 | B13: (to map) | C13: 2022-23 → 2025-26 | D13: 2022-23 → 2026-27 | E13: 2011-12 → 2025-26 | F13: 2011-12 → 2025-26 | G13: no data
A14: 10 | B14: (to map) | C14: 2022-23 → 2025-26 | D14: 2022-23 → 2026-27 | E14: 2011-12 → 2025-26 | F14: 2011-12 → 2025-26 | G14: no data
A15: 11 | B15: (to map) | C15: 2022-23 → 2025-26 | D15: 2022-23 → 2026-27 | E15: 2011-12 → 2025-26 | F15: 2011-12 → 2025-26 | G15: no data
A16: 12 | B16: (to map) | C16: 2022-23 → 2025-26 | D16: 2022-23 → 2026-27 | E16: 2011-12 → 2025-26 | F16: 2011-12 → 2025-26 | G16: no data
... A26: 22 | B26: (to map) | C26: 2023-24 → 2025-26 | D26: 2023-24 → 2026-27 | E26: 2012-13 → 2025-26 | F26: 2011-12 → 2025-26 | G26: no data

Sheet RBI_API_39
A1: RBI statistics available through the MoSPI API (39 indicators, from your step-1 file)
A2: History confirmed by your 02b re-test (11-Sep-2026). Frequency inferred from the period fields the API lists.
A4: Code | B4: Indicator | C4: Currency | D4: Frequency | E4: Earliest | F4: Latest | G4: Periods | H4: Status | I4: Your decision
A5: 1 | B5: Direction of Foreign Trade - Rupees | C5: ₹ | D5: Annual | E5: 2009-10 | F5: 2024-25 | G5: 16 | H5: Verified by your test
A6: 2 | B6: Exports of Select Commodities to Principal Countries - Rupees | C6: ₹ | D6: Annual | E6: 2013-14 | F6: 2024-25 | G6: 12 | H6: Verified by your test
A7: 4 | B7: India's Overall Balance of Payments - Quarterly - US Dollars | C7: US$ | D7: Quarterly | E7: 1990-91 | F7: 2025-26 | G7: 36 | H7: Verified by your test
A8: 5 | B8: India's Overall Balance of Payments - US Dollars | C8: US$ | D8: Annual | E8: 1990-91 | F8: 2024-25 | G8: 35 | H8: Verified by your test
A9: 6 | B9: India's Overall Balance of Payments – Rupees | C9: ₹ | D9: Annual | E9: 1990-91 | F9: 2024-25 | G9: 35 | H9: Verified by your test
A10: 7 | B10: Key Components of India's Balance of Payments – Rupees | C10: ₹ | D10: Annual | E10: 1950-51 | F10: 2024-25 | G10: 75 | H10: Verified by your test
A11: 8 | B11: Key Components of India's Balance of Payments - US Dollars | C11: US$ | D11: Annual | E11: 1950-51 | F11: 2024-25 | G11: 75 | H11: Verified by your test
A12: 9 | B12: Invisibles by Category of Transactions – US Dollars | C12: US$ | D12: Annual | E12: 1950-51 | F12: 2024-25 | G12: 75 | H12: Verified by your test
A13: 10 | B13: India’s Overall Balance of Payments – Quarterly – Rupees | C13: ₹ | D13: Quarterly | E13: 1990-91 | F13: 2025-26 | G13: 36 | H13: Verified by your test
A14: 11 | B14: Direction of Foreign Trade - US Dollars | C14: US$ | D14: Annual | E14: 2009-10 | F14: 2024-25 | G14: 16 | H14: Verified by your test
A15: 12 | B15: India's Foreign Trade - US Dollars | C15: US$ | D15: Monthly | E15: 1990-91 | F15: 2025-26 | G15: 36 | H15: Verified by your test
A16: 13 | B16: India's Foreign Trade – Rupees | C16: ₹ | D16: Monthly | E16: 1990-91 | F16: 2025-26 | G16: 36 | H16: Verified by your test
... A20: 20 | B20: Exports of Select Commodities to Principal Countries - US Dollars | C20: US$ | D20: Annual | E20: 2013-14 | F20: 2024-25 | G20: 12 | H20: Verified by your test
A21: 22 | B21: Balance of Payments - Indicators | D21: Annual | E21: 1970-71 | F21: 2024-25 | G21: 55 | H21: Verified by your test
A22: 24 | B22: Broad Commodity Composition of India's Merchandise Trade - Oil and Non oil Exports and Imports - Rupees | C22: ₹ | D22: Monthly | E22: 1997-98 | F22: 2025-26 | G22: 29 | H22: Verified by your test
A23: 25 | B23: India's External Debt - US Dollars (End-March) | C23: US$ | D23: Annual | E23: 1991 | F23: 2025 | G23: 35 | H23: Verified by your test
A24: 26 | B24: India's External Debt - Rupees (End-March) | C24: ₹ | D24: Annual | E24: 1991 | F24: 2025 | G24: 35 | H24: Verified by your test
A25: 27 | B25: External Debt of India - Quarterly | D25: Quarterly | E25: 2021 | F25: 2025 | G25: 5 | H25: Verified by your test
A26: 28 | B26: Sale/ Purchase of U.S. Dollar by the RBI | D26: Monthly | E26: 1995 | F26: 2025 | G26: 31 | H26: Verified by your test
A27: 29 | B27: Forex Rates - Month-High / Month-Low | D27: Monthly | E27: 1998 | F27: 2024 | G27: 27 | H27: Verified by your test
A28: 30 | B28: Turnover in Foreign Exchange Market | D28: Monthly | E28: 1996-97 | F28: 2025-26 | G28: 30 | H28: Verified by your test
A29: 31 | B29: Exchange Rate of the Indian Rupee Vis-A-Vis the SDR, US Dollar, Pound Sterling, D.M./Euro and Japanese Yen (Financial Year - Annual Average and End-Year Rates) | C29: US$ | D29: Annual | E29: 1970-71 | F29: 2024-25 | G29: 55 | H29: Verified by your test
A30: 32 | B30: Exchange Rate of the Indian Rupee Vis-a-Vis the SDR, US Dollar, Pound Sterling, D.M./Euro and Japanese Yen (Calendar Year - Annual Average) | C30: US$ | D30: Annual | E30: 1970 | F30: 2024 | G30: 55 | H30: Verified by your test
A31: 33 | B31: Exchange Rate of the Indian Rupee vis-à-vis the SDR, US Dollar, Pound Sterling, Euro and Japanese Yen (Monthly Average and end-Month Rates) | C31: US$ | D31: Monthly | E31: 1992 | F31: 2025 | G31: 34 | H31: Verified by your test
A32: 34 | B32: Forward Premia (Inter-Bank) (Monthly Average) | D32: Monthly | E32: 1993 | F32: 2025 | G32: 33 | H32: Verified by your test
A33: 35 | B33: Exchange Rate of the Indian Rupee vis-à-vis the SDR, US Dollar, Pound Sterling, Euro and Japanese Yen (High and Low During the Month) | C33: US$ | D33: Monthly | E33: 2008 | F33: 2025 | G33: 18 | H33: Verified by your test
A34: 36 | B34: Monthly Average Exchange Rates (EURO, GBP, JPY, USD) | C34: US$ | D34: Monthly | E34: 1966 | F34: 2025 | G34: 60 | H34: Verified by your test
A35: 37 | B35: Monthly Average Exchange Rate (155 Currencies) | D35: Monthly | E35: 2025 | F35: 2025 | G35: 1 | H35: Verified by your test
A36: 40 | B36: NRI Deposits - Outstandings and Inflows(+) / Outflows(-) | D36: Monthly | E36: 1997-98 | F36: 2025-26 | G36: 29 | H36: Verified by your test
A37: 42 | B37: Broad Commodity Composition of India’s Merchandise Trade - Oil and Non-Oil Exports and Imports - US Dollar | C37: US$ | D37: Monthly | E37: 1997-98 | F37: 2025-26 | G37: 29 | H37: Verified by your test
A38: 43 | B38: EXPORTS OF MAJOR COMMODITIES - RUPEES | C38: ₹ | D38: Annual | E38: 2009-10 | F38: 2024-25 | G38: 16 | H38: Verified by your test
A39: 44 | B39: EXPORTS OF MAJOR COMMODITIES - US Dollars | C39: US$ | D39: Annual | E39: 2009-10 | F39: 2024-25 | G39: 16 | H39: Verified by your test
A40: 45 | B40: Imports of Major Commodities - Rupees | C40: ₹ | D40: Annual | E40: 2009-10 | F40: 2024-25 | G40: 16 | H40: Verified by your test
A41: 46 | B41: Imports of Major Commodities - US Dollars | C41: US$ | D41: Annual | E41: 2009-10 | F41: 2024-25 | G41: 16 | H41: Verified by your test
A42: 47 | B42: Foreign Exchange Reserve Monthly | D42: Monthly | E42: 1990 | F42: 2025 | G42: 36 | H42: Verified by your test
A43: 48 | B43: Foreign Exchange Reserve Annual | D43: Annual | E43: 1950-51 | F43: 2024-25 | G43: 75 | H43: Verified by your test

Sheet YAHOO_TICKERS
A1: Yahoo Finance tickers to test (script 03_yfinance_explore.py)
A2: Unofficial API. Results from your script-03 run on 11-Sep-2026 (42 of 43 worked).
A4: Ticker | B4: Name | C4: Category | D4: Works? (Y/N) | E4: First date | F4: Your decision
A5: ^NSEI | B5: Nifty 50 | C5: Indian index | D5: Y | E5: 39342
A6: ^BSESN | B6: Sensex | C6: Indian index | D6: Y | E6: 35612
A7: ^NSEBANK | B7: Nifty Bank | C7: Indian sector | D7: Y | E7: 39342
A8: ^CNXIT | B8: Nifty IT | C8: Indian sector | D8: Y | E8: 39342
A9: ^CNXAUTO | B9: Nifty Auto | C9: Indian sector | D9: Y | E9: 40736
A10: ^CNXFMCG | B10: Nifty FMCG | C10: Indian sector | D10: Y | E10: 40574
A11: ^CNXPHARMA | B11: Nifty Pharma | C11: Indian sector | D11: Y | E11: 40574
A12: ^CNXMETAL | B12: Nifty Metal | C12: Indian sector | D12: Y | E12: 40736
A13: ^CNXREALTY | B13: Nifty Realty | C13: Indian sector | D13: Y | E13: 40378
A14: ^CNXENERGY | B14: Nifty Energy | C14: Indian sector | D14: Y | E14: 40574
A15: ^CNXPSUBANK | B15: Nifty PSU Bank | C15: Indian sector | D15: Y | E15: 40574
A16: ^CNXINFRA | B16: Nifty Infra | C16: Indian sector | D16: Y | E16: 40378
... A18: ^NSEMDCP50 | B18: Nifty Midcap 50 | C18: Indian broad market | D18: Y | E18: 39349
A19: ^CNXSC | B19: Nifty Smallcap 100 | C19: Indian broad market | D19: N | F19: Ticker no longer works – drop
A20: ^CRSLDX | B20: Nifty 500 | C20: Indian broad market | D20: Y | E20: 38621
A21: ^INDIAVIX | B21: India VIX | C21: Indian volatility | D21: Y | E21: 39510
A22: NIFTYBEES.NS | B22: Nifty BeES ETF | C22: Indian ETF | D22: Y | E22: 39815
A23: GOLDBEES.NS | B23: Gold BeES ETF | C23: Indian ETF | D23: Y | E23: 39815
A24: RELIANCE.NS | B24: Reliance (NSE) | C24: Indian stock | D24: Y | E24: 35065
A25: HDFCBANK.NS | B25: HDFC Bank (NSE) | C25: Indian stock | D25: Y | E25: 35065
A26: 500325.BO | B26: Reliance (BSE) | C26: Indian stock | D26: Y | E26: 34890
A27: INR=X | B27: USD/INR | C27: Currency | D27: Y | E27: 37956
A28: EURINR=X | B28: EUR/INR | C28: Currency | D28: Y | E28: 37956
A29: GBPINR=X | B29: GBP/INR | C29: Currency | D29: Y | E29: 38853
A30: JPYINR=X | B30: JPY/INR | C30: Currency | D30: Y | E30: 37956
A31: CNYINR=X | B31: CNY/INR | C31: Currency | D31: N | F31: Only 1 row – drop
A32: AEDINR=X | B32: AED/INR | C32: Currency | D32: Y | E32: 38476
A33: GC=F | B33: Gold | C33: Commodity | D33: Y | E33: 36768
A34: SI=F | B34: Silver | C34: Commodity | D34: Y | E34: 36768
A35: CL=F | B35: WTI crude | C35: Commodity | D35: Y | E35: 36761
A36: BZ=F | B36: Brent crude | C36: Commodity | D36: Y | E36: 39293
A37: NG=F | B37: Natural gas | C37: Commodity | D37: Y | E37: 36768
A38: HG=F | B38: Copper | C38: Commodity | D38: Y | E38: 36768
A39: ^GSPC | B39: S&P 500 | C39: Global index | D39: Y | E39: 10226
A40: ^IXIC | B40: Nasdaq | C40: Global index | D40: Y | E40: 25969
A41: ^DJI | B41: Dow Jones | C41: Global index | D41: Y | E41: 33605
A42: ^N225 | B42: Nikkei 225 | C42: Global index | D42: Y | E42: 23747
A43: ^HSI | B43: Hang Seng | C43: Global index | D43: Y | E43: 31777
... A47: ^VIX | B47: US VIX | C47: Global macro | D47: Y | E47: 32875

Sheet FUTURE_PROOFING
A1: Design principles that keep the tracker versatile and future-proof
A3: # | B3: Principle | C3: What it means in practice | D3: Why it matters
A4: 1 | B4: Catalogue-driven | C4: Every series is a row in the database's series table (and this workbook). Adding an indicator = adding a row + small config, not rewriting code. | D4: The list will grow to thousands of series; code must not grow with it.
A5: 2 | B5: One adapter per source | C5: MoSPI, RBI, FBIL, AMFI, Yahoo, data.gov.in… each has its own small module with the same interface: fetch → standardise → validate → save. | D5: A source changing its website breaks one module, never the whole pipeline.
A6: 3 | B6: Primary + fallback source | C6: e.g. USD/INR: FBIL primary, Yahoo fallback; forex reserves: RBI weekly primary, MoSPI-RBI monthly fallback. | D6: Government sites go down (NAS list endpoint returned HTTP 500 during your test).
A7: 4 | B7: Keep every vintage | C7: Never overwrite. Each value stores when it was fetched and its estimate stage (advance / provisional / revised). | D7: Lets you ask 'what did we know on date X' and study revisions (GDP, EPFO, IIP are revised often).
A8: 5 | B8: Base-year aware | C8: Base year is part of a series' identity; old and new bases stored separately; linked series computed from official linking factors. | D8: All four headline series (GDP, CPI, IIP, WPI) were rebased in 2026 – it will happen again.
A9: 6 | B9: Rich, standard metadata | C9: Unit and scale (₹ crore / lakh / US$ mn), price basis (current / constant), SA vs NSA, frequency, FY vs calendar year, classification (NIC, HS, COICOP). | D9: Stops silent mistakes like adding crore to million, or mixing FY and calendar quarters.
A10: 7 | B10: Standard codes for places | C10: One master table of state/UT and district codes (LGD codes) that every source maps into. | D10: Makes state and district dashboards possible across all sources.
A11: 8 | B11: Raw archive | C11: Save the raw file/response of every download (compressed) before parsing. | D11: If a parser bug is found later, you re-parse history instead of losing it.
A12: 9 | B12: Release calendar + staleness alerts | C12: Store the expected release date for each series; alert when a series is late. | D12: A silently broken scraper is worse than a loud one.
A13: 10 | B13: Quality checks on arrival | C13: Range checks, sudden-jump detection, duplicate periods, unit mismatch; cross-check sources (e.g. trade: Commerce vs RBI). | D13: Catch bad data before the team uses it.
A14: 11 | B14: Pagination & storage | C14: MoSPI returns 10 rows per page by default – always paginate. Very granular data (daily mandi rows, CPI item × state) goes to separate raw tables, partitioned by year if large. PostgreSQL on the VPS (~100 GB) has ample room; monitor disk monthly. | D14: Your tests showed both issues – design for them now.
A15: 12 | B15: Private by default | C15: PostgreSQL never exposed to the internet (localhost + SSH tunnel); separate read/write roles; Google Sheets shared only with named team members; no public API. | D15: Internal-only use; also keeps licensed/unofficial data (PMI, Yahoo) inside the team.
... A18: 15 | B18: Derived layer separate from raw | C18: Growth rates, SA series, ratios, composites are computed in views/jobs from raw data – never typed in. | D18: Recomputes automatically when raw data is revised.
